{"numTotalTestSuites":4,"numPassedTestSuites":0,"numFailedTestSuites":4,"numPendingTestSuites":0,"numTotalTests":44,"numPassedTests":27,"numFailedTests":17,"numPendingTests":0,"numTodoTests":0,"snapshot":{"added":0,"failure":false,"filesAdded":0,"filesRemoved":0,"filesRemovedList":[],"filesUnmatched":0,"filesUpdated":0,"matched":0,"total":0,"unchecked":0,"uncheckedKeysByFile":[],"unmatched":0,"updated":0,"didUpdate":false},"startTime":1776051168644,"success":false,"testResults":[{"assertionResults":[{"ancestorTitles":["Exercício 01"],"fullName":"Exercício 01 Ex01 - Válida - Questão 1","status":"passed","title":"Ex01 - Válida - Questão 1","duration":2.5016750000000343,"failureMessages":[],"meta":{}},{"ancestorTitles":["Exercício 01"],"fullName":"Exercício 01 Ex01 - Correta - Questão 1","status":"passed","title":"Ex01 - Correta - Questão 1","duration":1.3575060000000008,"failureMessages":[],"meta":{}},{"ancestorTitles":["Exercício 01"],"fullName":"Exercício 01 Ex01 - Válida - Questão 2","status":"passed","title":"Ex01 - Válida - Questão 2","duration":0.5040769999999952,"failureMessages":[],"meta":{}},{"ancestorTitles":["Exercício 01"],"fullName":"Exercício 01 Ex01 - Correta - Questão 2","status":"passed","title":"Ex01 - Correta - Questão 2","duration":0.8794330000000059,"failureMessages":[],"meta":{}},{"ancestorTitles":["Exercício 01"],"fullName":"Exercício 01 Ex01 - Válida - Questão 3","status":"passed","title":"Ex01 - Válida - Questão 3","duration":0.3473989999999958,"failureMessages":[],"meta":{}},{"ancestorTitles":["Exercício 01"],"fullName":"Exercício 01 Ex01 - Correta - Questão 3","status":"passed","title":"Ex01 - Correta - Questão 3","duration":0.20582999999999174,"failureMessages":[],"meta":{}},{"ancestorTitles":["Exercício 01"],"fullName":"Exercício 01 Ex01 - Válida - Questão 4","status":"passed","title":"Ex01 - Válida - Questão 4","duration":0.3815450000000169,"failureMessages":[],"meta":{}},{"ancestorTitles":["Exercício 01"],"fullName":"Exercício 01 Ex01 - Correta - Questão 4","status":"passed","title":"Ex01 - Correta - Questão 4","duration":0.5274420000000077,"failureMessages":[],"meta":{}},{"ancestorTitles":["Exercício 01"],"fullName":"Exercício 01 Ex01 - Válida - Questão 5","status":"passed","title":"Ex01 - Válida - Questão 5","duration":0.9090180000000032,"failureMessages":[],"meta":{}},{"ancestorTitles":["Exercício 01"],"fullName":"Exercício 01 Ex01 - Correta - Questão 5","status":"passed","title":"Ex01 - Correta - Questão 5","duration":0.595751000000007,"failureMessages":[],"meta":{}},{"ancestorTitles":["Exercício 01"],"fullName":"Exercício 01 Ex01 - Válida - Questão 6","status":"passed","title":"Ex01 - Válida - Questão 6","duration":0.5045289999999909,"failureMessages":[],"meta":{}},{"ancestorTitles":["Exercício 01"],"fullName":"Exercício 01 Ex01 - Correta - Questão 6","status":"failed","title":"Ex01 - Correta - Questão 6","duration":17.990028000000052,"failureMessages":["AssertionError: expected [ undefined, undefined, …(3) ] to deeply equal [ 'Ana', 'Carla', 'Eduarda', …(2) ]\n    at /home/vicmca/CodeProjects/School/materiais/atv_pub/2c-04-lacos/ex01.test.js:40:29\n    at file:///home/vicmca/CodeProjects/School/materiais/atv_pub/2c-04-lacos/node_modules/@vitest/runner/dist/index.js:145:11\n    at file:///home/vicmca/CodeProjects/School/materiais/atv_pub/2c-04-lacos/node_modules/@vitest/runner/dist/index.js:915:26\n    at file:///home/vicmca/CodeProjects/School/materiais/atv_pub/2c-04-lacos/node_modules/@vitest/runner/dist/index.js:1243:20\n    at new Promise (<anonymous>)\n    at runWithTimeout (file:///home/vicmca/CodeProjects/School/materiais/atv_pub/2c-04-lacos/node_modules/@vitest/runner/dist/index.js:1209:10)\n    at file:///home/vicmca/CodeProjects/School/materiais/atv_pub/2c-04-lacos/node_modules/@vitest/runner/dist/index.js:1653:37\n    at Traces.$ (file:///home/vicmca/CodeProjects/School/materiais/atv_pub/2c-04-lacos/node_modules/vitest/dist/chunks/traces.CCmnQaNT.js:142:27)\n    at trace (file:///home/vicmca/CodeProjects/School/materiais/atv_pub/2c-04-lacos/node_modules/vitest/dist/chunks/test.B8ej_ZHS.js:239:21)\n    at runTest (file:///home/vicmca/CodeProjects/School/materiais/atv_pub/2c-04-lacos/node_modules/@vitest/runner/dist/index.js:1653:12)"],"meta":{}},{"ancestorTitles":["Exercício 01"],"fullName":"Exercício 01 Ex01 - Válida - Questão 7","status":"passed","title":"Ex01 - Válida - Questão 7","duration":0.284466000000009,"failureMessages":[],"meta":{}},{"ancestorTitles":["Exercício 01"],"fullName":"Exercício 01 Ex01 - Correta - Questão 7","status":"failed","title":"Ex01 - Correta - Questão 7","duration":2.4030500000000075,"failureMessages":["AssertionError: expected [ undefined, undefined, …(4) ] to deeply equal [ 'Ana', 'Bruno', 'Carla', …(3) ]\n    at /home/vicmca/CodeProjects/School/materiais/atv_pub/2c-04-lacos/ex01.test.js:40:29\n    at file:///home/vicmca/CodeProjects/School/materiais/atv_pub/2c-04-lacos/node_modules/@vitest/runner/dist/index.js:145:11\n    at file:///home/vicmca/CodeProjects/School/materiais/atv_pub/2c-04-lacos/node_modules/@vitest/runner/dist/index.js:915:26\n    at file:///home/vicmca/CodeProjects/School/materiais/atv_pub/2c-04-lacos/node_modules/@vitest/runner/dist/index.js:1243:20\n    at new Promise (<anonymous>)\n    at runWithTimeout (file:///home/vicmca/CodeProjects/School/materiais/atv_pub/2c-04-lacos/node_modules/@vitest/runner/dist/index.js:1209:10)\n    at file:///home/vicmca/CodeProjects/School/materiais/atv_pub/2c-04-lacos/node_modules/@vitest/runner/dist/index.js:1653:37\n    at Traces.$ (file:///home/vicmca/CodeProjects/School/materiais/atv_pub/2c-04-lacos/node_modules/vitest/dist/chunks/traces.CCmnQaNT.js:142:27)\n    at trace (file:///home/vicmca/CodeProjects/School/materiais/atv_pub/2c-04-lacos/node_modules/vitest/dist/chunks/test.B8ej_ZHS.js:239:21)\n    at runTest (file:///home/vicmca/CodeProjects/School/materiais/atv_pub/2c-04-lacos/node_modules/@vitest/runner/dist/index.js:1653:12)"],"meta":{}},{"ancestorTitles":["Exercício 01"],"fullName":"Exercício 01 Ex01 - Válida - Questão 8","status":"failed","title":"Ex01 - Válida - Questão 8","duration":1.171952000000033,"failureMessages":["AssertionError: expected false not to be type of 'boolean'\n    at /home/vicmca/CodeProjects/School/materiais/atv_pub/2c-04-lacos/ex01.test.js:36:33\n    at file:///home/vicmca/CodeProjects/School/materiais/atv_pub/2c-04-lacos/node_modules/@vitest/runner/dist/index.js:145:11\n    at file:///home/vicmca/CodeProjects/School/materiais/atv_pub/2c-04-lacos/node_modules/@vitest/runner/dist/index.js:915:26\n    at file:///home/vicmca/CodeProjects/School/materiais/atv_pub/2c-04-lacos/node_modules/@vitest/runner/dist/index.js:1243:20\n    at new Promise (<anonymous>)\n    at runWithTimeout (file:///home/vicmca/CodeProjects/School/materiais/atv_pub/2c-04-lacos/node_modules/@vitest/runner/dist/index.js:1209:10)\n    at file:///home/vicmca/CodeProjects/School/materiais/atv_pub/2c-04-lacos/node_modules/@vitest/runner/dist/index.js:1653:37\n    at Traces.$ (file:///home/vicmca/CodeProjects/School/materiais/atv_pub/2c-04-lacos/node_modules/vitest/dist/chunks/traces.CCmnQaNT.js:142:27)\n    at trace (file:///home/vicmca/CodeProjects/School/materiais/atv_pub/2c-04-lacos/node_modules/vitest/dist/chunks/test.B8ej_ZHS.js:239:21)\n    at runTest (file:///home/vicmca/CodeProjects/School/materiais/atv_pub/2c-04-lacos/node_modules/@vitest/runner/dist/index.js:1653:12)"],"meta":{}},{"ancestorTitles":["Exercício 01"],"fullName":"Exercício 01 Ex01 - Correta - Questão 8","status":"failed","title":"Ex01 - Correta - Questão 8","duration":1.46865600000001,"failureMessages":["AssertionError: expected false to deeply equal [ 'ANA', 'BRUNO', 'CARLA', …(7) ]\n    at /home/vicmca/CodeProjects/School/materiais/atv_pub/2c-04-lacos/ex01.test.js:40:29\n    at file:///home/vicmca/CodeProjects/School/materiais/atv_pub/2c-04-lacos/node_modules/@vitest/runner/dist/index.js:145:11\n    at file:///home/vicmca/CodeProjects/School/materiais/atv_pub/2c-04-lacos/node_modules/@vitest/runner/dist/index.js:915:26\n    at file:///home/vicmca/CodeProjects/School/materiais/atv_pub/2c-04-lacos/node_modules/@vitest/runner/dist/index.js:1243:20\n    at new Promise (<anonymous>)\n    at runWithTimeout (file:///home/vicmca/CodeProjects/School/materiais/atv_pub/2c-04-lacos/node_modules/@vitest/runner/dist/index.js:1209:10)\n    at file:///home/vicmca/CodeProjects/School/materiais/atv_pub/2c-04-lacos/node_modules/@vitest/runner/dist/index.js:1653:37\n    at Traces.$ (file:///home/vicmca/CodeProjects/School/materiais/atv_pub/2c-04-lacos/node_modules/vitest/dist/chunks/traces.CCmnQaNT.js:142:27)\n    at trace (file:///home/vicmca/CodeProjects/School/materiais/atv_pub/2c-04-lacos/node_modules/vitest/dist/chunks/test.B8ej_ZHS.js:239:21)\n    at runTest (file:///home/vicmca/CodeProjects/School/materiais/atv_pub/2c-04-lacos/node_modules/@vitest/runner/dist/index.js:1653:12)"],"meta":{}},{"ancestorTitles":["Exercício 01"],"fullName":"Exercício 01 Ex01 - Válida - Questão 9","status":"failed","title":"Ex01 - Válida - Questão 9","duration":1.0387289999999894,"failureMessages":["AssertionError: expected false not to be type of 'boolean'\n    at /home/vicmca/CodeProjects/School/materiais/atv_pub/2c-04-lacos/ex01.test.js:36:33\n    at file:///home/vicmca/CodeProjects/School/materiais/atv_pub/2c-04-lacos/node_modules/@vitest/runner/dist/index.js:145:11\n    at file:///home/vicmca/CodeProjects/School/materiais/atv_pub/2c-04-lacos/node_modules/@vitest/runner/dist/index.js:915:26\n    at file:///home/vicmca/CodeProjects/School/materiais/atv_pub/2c-04-lacos/node_modules/@vitest/runner/dist/index.js:1243:20\n    at new Promise (<anonymous>)\n    at runWithTimeout (file:///home/vicmca/CodeProjects/School/materiais/atv_pub/2c-04-lacos/node_modules/@vitest/runner/dist/index.js:1209:10)\n    at file:///home/vicmca/CodeProjects/School/materiais/atv_pub/2c-04-lacos/node_modules/@vitest/runner/dist/index.js:1653:37\n    at Traces.$ (file:///home/vicmca/CodeProjects/School/materiais/atv_pub/2c-04-lacos/node_modules/vitest/dist/chunks/traces.CCmnQaNT.js:142:27)\n    at trace (file:///home/vicmca/CodeProjects/School/materiais/atv_pub/2c-04-lacos/node_modules/vitest/dist/chunks/test.B8ej_ZHS.js:239:21)\n    at runTest (file:///home/vicmca/CodeProjects/School/materiais/atv_pub/2c-04-lacos/node_modules/@vitest/runner/dist/index.js:1653:12)"],"meta":{}},{"ancestorTitles":["Exercício 01"],"fullName":"Exercício 01 Ex01 - Correta - Questão 9","status":"failed","title":"Ex01 - Correta - Questão 9","duration":1.2066050000000246,"failureMessages":["AssertionError: expected false to deeply equal [ 'Ana', 'Eduarda', 'Isabela' ]\n    at /home/vicmca/CodeProjects/School/materiais/atv_pub/2c-04-lacos/ex01.test.js:40:29\n    at file:///home/vicmca/CodeProjects/School/materiais/atv_pub/2c-04-lacos/node_modules/@vitest/runner/dist/index.js:145:11\n    at file:///home/vicmca/CodeProjects/School/materiais/atv_pub/2c-04-lacos/node_modules/@vitest/runner/dist/index.js:915:26\n    at file:///home/vicmca/CodeProjects/School/materiais/atv_pub/2c-04-lacos/node_modules/@vitest/runner/dist/index.js:1243:20\n    at new Promise (<anonymous>)\n    at runWithTimeout (file:///home/vicmca/CodeProjects/School/materiais/atv_pub/2c-04-lacos/node_modules/@vitest/runner/dist/index.js:1209:10)\n    at file:///home/vicmca/CodeProjects/School/materiais/atv_pub/2c-04-lacos/node_modules/@vitest/runner/dist/index.js:1653:37\n    at Traces.$ (file:///home/vicmca/CodeProjects/School/materiais/atv_pub/2c-04-lacos/node_modules/vitest/dist/chunks/traces.CCmnQaNT.js:142:27)\n    at trace (file:///home/vicmca/CodeProjects/School/materiais/atv_pub/2c-04-lacos/node_modules/vitest/dist/chunks/test.B8ej_ZHS.js:239:21)\n    at runTest (file:///home/vicmca/CodeProjects/School/materiais/atv_pub/2c-04-lacos/node_modules/@vitest/runner/dist/index.js:1653:12)"],"meta":{}},{"ancestorTitles":["Exercício 01"],"fullName":"Exercício 01 Ex01 - Válida - Questão 10","status":"failed","title":"Ex01 - Válida - Questão 10","duration":0.9932110000000307,"failureMessages":["AssertionError: expected false not to be type of 'boolean'\n    at /home/vicmca/CodeProjects/School/materiais/atv_pub/2c-04-lacos/ex01.test.js:36:33\n    at file:///home/vicmca/CodeProjects/School/materiais/atv_pub/2c-04-lacos/node_modules/@vitest/runner/dist/index.js:145:11\n    at file:///home/vicmca/CodeProjects/School/materiais/atv_pub/2c-04-lacos/node_modules/@vitest/runner/dist/index.js:915:26\n    at file:///home/vicmca/CodeProjects/School/materiais/atv_pub/2c-04-lacos/node_modules/@vitest/runner/dist/index.js:1243:20\n    at new Promise (<anonymous>)\n    at runWithTimeout (file:///home/vicmca/CodeProjects/School/materiais/atv_pub/2c-04-lacos/node_modules/@vitest/runner/dist/index.js:1209:10)\n    at file:///home/vicmca/CodeProjects/School/materiais/atv_pub/2c-04-lacos/node_modules/@vitest/runner/dist/index.js:1653:37\n    at Traces.$ (file:///home/vicmca/CodeProjects/School/materiais/atv_pub/2c-04-lacos/node_modules/vitest/dist/chunks/traces.CCmnQaNT.js:142:27)\n    at trace (file:///home/vicmca/CodeProjects/School/materiais/atv_pub/2c-04-lacos/node_modules/vitest/dist/chunks/test.B8ej_ZHS.js:239:21)\n    at runTest (file:///home/vicmca/CodeProjects/School/materiais/atv_pub/2c-04-lacos/node_modules/@vitest/runner/dist/index.js:1653:12)"],"meta":{}},{"ancestorTitles":["Exercício 01"],"fullName":"Exercício 01 Ex01 - Correta - Questão 10","status":"failed","title":"Ex01 - Correta - Questão 10","duration":0.9321020000000431,"failureMessages":["AssertionError: expected false to deeply equal 'Gabriela'\n    at /home/vicmca/CodeProjects/School/materiais/atv_pub/2c-04-lacos/ex01.test.js:40:29\n    at file:///home/vicmca/CodeProjects/School/materiais/atv_pub/2c-04-lacos/node_modules/@vitest/runner/dist/index.js:145:11\n    at file:///home/vicmca/CodeProjects/School/materiais/atv_pub/2c-04-lacos/node_modules/@vitest/runner/dist/index.js:915:26\n    at file:///home/vicmca/CodeProjects/School/materiais/atv_pub/2c-04-lacos/node_modules/@vitest/runner/dist/index.js:1243:20\n    at new Promise (<anonymous>)\n    at runWithTimeout (file:///home/vicmca/CodeProjects/School/materiais/atv_pub/2c-04-lacos/node_modules/@vitest/runner/dist/index.js:1209:10)\n    at file:///home/vicmca/CodeProjects/School/materiais/atv_pub/2c-04-lacos/node_modules/@vitest/runner/dist/index.js:1653:37\n    at Traces.$ (file:///home/vicmca/CodeProjects/School/materiais/atv_pub/2c-04-lacos/node_modules/vitest/dist/chunks/traces.CCmnQaNT.js:142:27)\n    at trace (file:///home/vicmca/CodeProjects/School/materiais/atv_pub/2c-04-lacos/node_modules/vitest/dist/chunks/test.B8ej_ZHS.js:239:21)\n    at runTest (file:///home/vicmca/CodeProjects/School/materiais/atv_pub/2c-04-lacos/node_modules/@vitest/runner/dist/index.js:1653:12)"],"meta":{}}],"startTime":1776051169006,"endTime":1776051169042.9321,"status":"failed","message":"","name":"/home/vicmca/CodeProjects/School/materiais/atv_pub/2c-04-lacos/ex01.test.js"},{"assertionResults":[{"ancestorTitles":["Exercício 02"],"fullName":"Exercício 02 Ex02 - Válida - Questão 1","status":"passed","title":"Ex02 - Válida - Questão 1","duration":3.7594310000000064,"failureMessages":[],"meta":{}},{"ancestorTitles":["Exercício 02"],"fullName":"Exercício 02 Ex02 - Correta - Questão 1","status":"passed","title":"Ex02 - Correta - Questão 1","duration":1.895038999999997,"failureMessages":[],"meta":{}},{"ancestorTitles":["Exercício 02"],"fullName":"Exercício 02 Ex02 - Válida - Questão 2","status":"passed","title":"Ex02 - Válida - Questão 2","duration":0.35487799999998515,"failureMessages":[],"meta":{}},{"ancestorTitles":["Exercício 02"],"fullName":"Exercício 02 Ex02 - Correta - Questão 2","status":"passed","title":"Ex02 - Correta - Questão 2","duration":0.6868129999999724,"failureMessages":[],"meta":{}},{"ancestorTitles":["Exercício 02"],"fullName":"Exercício 02 Ex02 - Válida - Questão 3","status":"passed","title":"Ex02 - Válida - Questão 3","duration":0.3355470000000196,"failureMessages":[],"meta":{}},{"ancestorTitles":["Exercício 02"],"fullName":"Exercício 02 Ex02 - Correta - Questão 3","status":"passed","title":"Ex02 - Correta - Questão 3","duration":0.2304009999999721,"failureMessages":[],"meta":{}},{"ancestorTitles":["Exercício 02"],"fullName":"Exercício 02 Ex02 - Válida - Questão 4","status":"passed","title":"Ex02 - Válida - Questão 4","duration":0.3830330000000117,"failureMessages":[],"meta":{}},{"ancestorTitles":["Exercício 02"],"fullName":"Exercício 02 Ex02 - Correta - Questão 4","status":"failed","title":"Ex02 - Correta - Questão 4","duration":13.001959,"failureMessages":["AssertionError: expected 99 to deeply equal 100.5\n    at /home/vicmca/CodeProjects/School/materiais/atv_pub/2c-04-lacos/ex02.test.js:45:30\n    at file:///home/vicmca/CodeProjects/School/materiais/atv_pub/2c-04-lacos/node_modules/@vitest/runner/dist/index.js:145:11\n    at file:///home/vicmca/CodeProjects/School/materiais/atv_pub/2c-04-lacos/node_modules/@vitest/runner/dist/index.js:915:26\n    at file:///home/vicmca/CodeProjects/School/materiais/atv_pub/2c-04-lacos/node_modules/@vitest/runner/dist/index.js:1243:20\n    at new Promise (<anonymous>)\n    at runWithTimeout (file:///home/vicmca/CodeProjects/School/materiais/atv_pub/2c-04-lacos/node_modules/@vitest/runner/dist/index.js:1209:10)\n    at file:///home/vicmca/CodeProjects/School/materiais/atv_pub/2c-04-lacos/node_modules/@vitest/runner/dist/index.js:1653:37\n    at Traces.$ (file:///home/vicmca/CodeProjects/School/materiais/atv_pub/2c-04-lacos/node_modules/vitest/dist/chunks/traces.CCmnQaNT.js:142:27)\n    at trace (file:///home/vicmca/CodeProjects/School/materiais/atv_pub/2c-04-lacos/node_modules/vitest/dist/chunks/test.B8ej_ZHS.js:239:21)\n    at runTest (file:///home/vicmca/CodeProjects/School/materiais/atv_pub/2c-04-lacos/node_modules/@vitest/runner/dist/index.js:1653:12)"],"meta":{}},{"ancestorTitles":["Exercício 02"],"fullName":"Exercício 02 Ex02 - Válida - Questão 5","status":"passed","title":"Ex02 - Válida - Questão 5","duration":0.7012740000000122,"failureMessages":[],"meta":{}},{"ancestorTitles":["Exercício 02"],"fullName":"Exercício 02 Ex02 - Correta - Questão 5","status":"passed","title":"Ex02 - Correta - Questão 5","duration":0.7885820000000194,"failureMessages":[],"meta":{}},{"ancestorTitles":["Exercício 02"],"fullName":"Exercício 02 Ex02 - Válida - Questão 6","status":"passed","title":"Ex02 - Válida - Questão 6","duration":0.27401099999997314,"failureMessages":[],"meta":{}},{"ancestorTitles":["Exercício 02"],"fullName":"Exercício 02 Ex02 - Correta - Questão 6","status":"passed","title":"Ex02 - Correta - Questão 6","duration":0.2776400000000194,"failureMessages":[],"meta":{}},{"ancestorTitles":["Exercício 02"],"fullName":"Exercício 02 Ex02 - Válida - Questão 7","status":"passed","title":"Ex02 - Válida - Questão 7","duration":0.391633000000013,"failureMessages":[],"meta":{}},{"ancestorTitles":["Exercício 02"],"fullName":"Exercício 02 Ex02 - Correta - Questão 7","status":"passed","title":"Ex02 - Correta - Questão 7","duration":0.6408070000000521,"failureMessages":[],"meta":{}},{"ancestorTitles":["Exercício 02"],"fullName":"Exercício 02 Ex02 - Válida - Questão 8","status":"passed","title":"Ex02 - Válida - Questão 8","duration":0.3377179999999953,"failureMessages":[],"meta":{}},{"ancestorTitles":["Exercício 02"],"fullName":"Exercício 02 Ex02 - Correta - Questão 8","status":"passed","title":"Ex02 - Correta - Questão 8","duration":0.23020999999999958,"failureMessages":[],"meta":{}},{"ancestorTitles":["Exercício 02"],"fullName":"Exercício 02 Ex02 - Válida - Questão 9","status":"failed","title":"Ex02 - Válida - Questão 9","duration":1.7430099999999698,"failureMessages":["AssertionError: expected false not to be type of 'boolean'\n    at /home/vicmca/CodeProjects/School/materiais/atv_pub/2c-04-lacos/ex02.test.js:41:34\n    at file:///home/vicmca/CodeProjects/School/materiais/atv_pub/2c-04-lacos/node_modules/@vitest/runner/dist/index.js:145:11\n    at file:///home/vicmca/CodeProjects/School/materiais/atv_pub/2c-04-lacos/node_modules/@vitest/runner/dist/index.js:915:26\n    at file:///home/vicmca/CodeProjects/School/materiais/atv_pub/2c-04-lacos/node_modules/@vitest/runner/dist/index.js:1243:20\n    at new Promise (<anonymous>)\n    at runWithTimeout (file:///home/vicmca/CodeProjects/School/materiais/atv_pub/2c-04-lacos/node_modules/@vitest/runner/dist/index.js:1209:10)\n    at file:///home/vicmca/CodeProjects/School/materiais/atv_pub/2c-04-lacos/node_modules/@vitest/runner/dist/index.js:1653:37\n    at Traces.$ (file:///home/vicmca/CodeProjects/School/materiais/atv_pub/2c-04-lacos/node_modules/vitest/dist/chunks/traces.CCmnQaNT.js:142:27)\n    at trace (file:///home/vicmca/CodeProjects/School/materiais/atv_pub/2c-04-lacos/node_modules/vitest/dist/chunks/test.B8ej_ZHS.js:239:21)\n    at runTest (file:///home/vicmca/CodeProjects/School/materiais/atv_pub/2c-04-lacos/node_modules/@vitest/runner/dist/index.js:1653:12)"],"meta":{}},{"ancestorTitles":["Exercício 02"],"fullName":"Exercício 02 Ex02 - Correta - Questão 9","status":"failed","title":"Ex02 - Correta - Questão 9","duration":3.6879000000000133,"failureMessages":["AssertionError: expected false to deeply equal [ 'LAGARTO', 'TARÂNTULA', …(8) ]\n    at /home/vicmca/CodeProjects/School/materiais/atv_pub/2c-04-lacos/ex02.test.js:45:30\n    at file:///home/vicmca/CodeProjects/School/materiais/atv_pub/2c-04-lacos/node_modules/@vitest/runner/dist/index.js:145:11\n    at file:///home/vicmca/CodeProjects/School/materiais/atv_pub/2c-04-lacos/node_modules/@vitest/runner/dist/index.js:915:26\n    at file:///home/vicmca/CodeProjects/School/materiais/atv_pub/2c-04-lacos/node_modules/@vitest/runner/dist/index.js:1243:20\n    at new Promise (<anonymous>)\n    at runWithTimeout (file:///home/vicmca/CodeProjects/School/materiais/atv_pub/2c-04-lacos/node_modules/@vitest/runner/dist/index.js:1209:10)\n    at file:///home/vicmca/CodeProjects/School/materiais/atv_pub/2c-04-lacos/node_modules/@vitest/runner/dist/index.js:1653:37\n    at Traces.$ (file:///home/vicmca/CodeProjects/School/materiais/atv_pub/2c-04-lacos/node_modules/vitest/dist/chunks/traces.CCmnQaNT.js:142:27)\n    at trace (file:///home/vicmca/CodeProjects/School/materiais/atv_pub/2c-04-lacos/node_modules/vitest/dist/chunks/test.B8ej_ZHS.js:239:21)\n    at runTest (file:///home/vicmca/CodeProjects/School/materiais/atv_pub/2c-04-lacos/node_modules/@vitest/runner/dist/index.js:1653:12)"],"meta":{}},{"ancestorTitles":["Exercício 02"],"fullName":"Exercício 02 Ex02 - Válida - Questão 10","status":"failed","title":"Ex02 - Válida - Questão 10","duration":1.3181280000000015,"failureMessages":["AssertionError: expected false not to be type of 'boolean'\n    at /home/vicmca/CodeProjects/School/materiais/atv_pub/2c-04-lacos/ex02.test.js:41:34\n    at file:///home/vicmca/CodeProjects/School/materiais/atv_pub/2c-04-lacos/node_modules/@vitest/runner/dist/index.js:145:11\n    at file:///home/vicmca/CodeProjects/School/materiais/atv_pub/2c-04-lacos/node_modules/@vitest/runner/dist/index.js:915:26\n    at file:///home/vicmca/CodeProjects/School/materiais/atv_pub/2c-04-lacos/node_modules/@vitest/runner/dist/index.js:1243:20\n    at new Promise (<anonymous>)\n    at runWithTimeout (file:///home/vicmca/CodeProjects/School/materiais/atv_pub/2c-04-lacos/node_modules/@vitest/runner/dist/index.js:1209:10)\n    at file:///home/vicmca/CodeProjects/School/materiais/atv_pub/2c-04-lacos/node_modules/@vitest/runner/dist/index.js:1653:37\n    at Traces.$ (file:///home/vicmca/CodeProjects/School/materiais/atv_pub/2c-04-lacos/node_modules/vitest/dist/chunks/traces.CCmnQaNT.js:142:27)\n    at trace (file:///home/vicmca/CodeProjects/School/materiais/atv_pub/2c-04-lacos/node_modules/vitest/dist/chunks/test.B8ej_ZHS.js:239:21)\n    at runTest (file:///home/vicmca/CodeProjects/School/materiais/atv_pub/2c-04-lacos/node_modules/@vitest/runner/dist/index.js:1653:12)"],"meta":{}},{"ancestorTitles":["Exercício 02"],"fullName":"Exercício 02 Ex02 - Correta - Questão 10","status":"failed","title":"Ex02 - Correta - Questão 10","duration":1.671088999999995,"failureMessages":["AssertionError: expected false to deeply equal [ 'lagarto', 'tarântula', …(4) ]\n    at /home/vicmca/CodeProjects/School/materiais/atv_pub/2c-04-lacos/ex02.test.js:45:30\n    at file:///home/vicmca/CodeProjects/School/materiais/atv_pub/2c-04-lacos/node_modules/@vitest/runner/dist/index.js:145:11\n    at file:///home/vicmca/CodeProjects/School/materiais/atv_pub/2c-04-lacos/node_modules/@vitest/runner/dist/index.js:915:26\n    at file:///home/vicmca/CodeProjects/School/materiais/atv_pub/2c-04-lacos/node_modules/@vitest/runner/dist/index.js:1243:20\n    at new Promise (<anonymous>)\n    at runWithTimeout (file:///home/vicmca/CodeProjects/School/materiais/atv_pub/2c-04-lacos/node_modules/@vitest/runner/dist/index.js:1209:10)\n    at file:///home/vicmca/CodeProjects/School/materiais/atv_pub/2c-04-lacos/node_modules/@vitest/runner/dist/index.js:1653:37\n    at Traces.$ (file:///home/vicmca/CodeProjects/School/materiais/atv_pub/2c-04-lacos/node_modules/vitest/dist/chunks/traces.CCmnQaNT.js:142:27)\n    at trace (file:///home/vicmca/CodeProjects/School/materiais/atv_pub/2c-04-lacos/node_modules/vitest/dist/chunks/test.B8ej_ZHS.js:239:21)\n    at runTest (file:///home/vicmca/CodeProjects/School/materiais/atv_pub/2c-04-lacos/node_modules/@vitest/runner/dist/index.js:1653:12)"],"meta":{}},{"ancestorTitles":["Exercício 02"],"fullName":"Exercício 02 Ex02 - Válida - Questão 11","status":"failed","title":"Ex02 - Válida - Questão 11","duration":1.1682680000000119,"failureMessages":["AssertionError: expected false not to be type of 'boolean'\n    at /home/vicmca/CodeProjects/School/materiais/atv_pub/2c-04-lacos/ex02.test.js:41:34\n    at file:///home/vicmca/CodeProjects/School/materiais/atv_pub/2c-04-lacos/node_modules/@vitest/runner/dist/index.js:145:11\n    at file:///home/vicmca/CodeProjects/School/materiais/atv_pub/2c-04-lacos/node_modules/@vitest/runner/dist/index.js:915:26\n    at file:///home/vicmca/CodeProjects/School/materiais/atv_pub/2c-04-lacos/node_modules/@vitest/runner/dist/index.js:1243:20\n    at new Promise (<anonymous>)\n    at runWithTimeout (file:///home/vicmca/CodeProjects/School/materiais/atv_pub/2c-04-lacos/node_modules/@vitest/runner/dist/index.js:1209:10)\n    at file:///home/vicmca/CodeProjects/School/materiais/atv_pub/2c-04-lacos/node_modules/@vitest/runner/dist/index.js:1653:37\n    at Traces.$ (file:///home/vicmca/CodeProjects/School/materiais/atv_pub/2c-04-lacos/node_modules/vitest/dist/chunks/traces.CCmnQaNT.js:142:27)\n    at trace (file:///home/vicmca/CodeProjects/School/materiais/atv_pub/2c-04-lacos/node_modules/vitest/dist/chunks/test.B8ej_ZHS.js:239:21)\n    at runTest (file:///home/vicmca/CodeProjects/School/materiais/atv_pub/2c-04-lacos/node_modules/@vitest/runner/dist/index.js:1653:12)"],"meta":{}},{"ancestorTitles":["Exercício 02"],"fullName":"Exercício 02 Ex02 - Correta - Questão 11","status":"failed","title":"Ex02 - Correta - Questão 11","duration":1.1988269999999943,"failureMessages":["AssertionError: expected false to deeply equal 4\n    at /home/vicmca/CodeProjects/School/materiais/atv_pub/2c-04-lacos/ex02.test.js:45:30\n    at file:///home/vicmca/CodeProjects/School/materiais/atv_pub/2c-04-lacos/node_modules/@vitest/runner/dist/index.js:145:11\n    at file:///home/vicmca/CodeProjects/School/materiais/atv_pub/2c-04-lacos/node_modules/@vitest/runner/dist/index.js:915:26\n    at file:///home/vicmca/CodeProjects/School/materiais/atv_pub/2c-04-lacos/node_modules/@vitest/runner/dist/index.js:1243:20\n    at new Promise (<anonymous>)\n    at runWithTimeout (file:///home/vicmca/CodeProjects/School/materiais/atv_pub/2c-04-lacos/node_modules/@vitest/runner/dist/index.js:1209:10)\n    at file:///home/vicmca/CodeProjects/School/materiais/atv_pub/2c-04-lacos/node_modules/@vitest/runner/dist/index.js:1653:37\n    at Traces.$ (file:///home/vicmca/CodeProjects/School/materiais/atv_pub/2c-04-lacos/node_modules/vitest/dist/chunks/traces.CCmnQaNT.js:142:27)\n    at trace (file:///home/vicmca/CodeProjects/School/materiais/atv_pub/2c-04-lacos/node_modules/vitest/dist/chunks/test.B8ej_ZHS.js:239:21)\n    at runTest (file:///home/vicmca/CodeProjects/School/materiais/atv_pub/2c-04-lacos/node_modules/@vitest/runner/dist/index.js:1653:12)"],"meta":{}},{"ancestorTitles":["Exercício 02"],"fullName":"Exercício 02 Ex02 - Válida - Questão 12","status":"failed","title":"Ex02 - Válida - Questão 12","duration":0.9175040000000081,"failureMessages":["AssertionError: expected false not to be type of 'boolean'\n    at /home/vicmca/CodeProjects/School/materiais/atv_pub/2c-04-lacos/ex02.test.js:41:34\n    at file:///home/vicmca/CodeProjects/School/materiais/atv_pub/2c-04-lacos/node_modules/@vitest/runner/dist/index.js:145:11\n    at file:///home/vicmca/CodeProjects/School/materiais/atv_pub/2c-04-lacos/node_modules/@vitest/runner/dist/index.js:915:26\n    at file:///home/vicmca/CodeProjects/School/materiais/atv_pub/2c-04-lacos/node_modules/@vitest/runner/dist/index.js:1243:20\n    at new Promise (<anonymous>)\n    at runWithTimeout (file:///home/vicmca/CodeProjects/School/materiais/atv_pub/2c-04-lacos/node_modules/@vitest/runner/dist/index.js:1209:10)\n    at file:///home/vicmca/CodeProjects/School/materiais/atv_pub/2c-04-lacos/node_modules/@vitest/runner/dist/index.js:1653:37\n    at Traces.$ (file:///home/vicmca/CodeProjects/School/materiais/atv_pub/2c-04-lacos/node_modules/vitest/dist/chunks/traces.CCmnQaNT.js:142:27)\n    at trace (file:///home/vicmca/CodeProjects/School/materiais/atv_pub/2c-04-lacos/node_modules/vitest/dist/chunks/test.B8ej_ZHS.js:239:21)\n    at runTest (file:///home/vicmca/CodeProjects/School/materiais/atv_pub/2c-04-lacos/node_modules/@vitest/runner/dist/index.js:1653:12)"],"meta":{}},{"ancestorTitles":["Exercício 02"],"fullName":"Exercício 02 Ex02 - Correta - Questão 12","status":"failed","title":"Ex02 - Correta - Questão 12","duration":1.6521359999999845,"failureMessages":["AssertionError: expected false to deeply equal 'sagui'\n    at /home/vicmca/CodeProjects/School/materiais/atv_pub/2c-04-lacos/ex02.test.js:45:30\n    at file:///home/vicmca/CodeProjects/School/materiais/atv_pub/2c-04-lacos/node_modules/@vitest/runner/dist/index.js:145:11\n    at file:///home/vicmca/CodeProjects/School/materiais/atv_pub/2c-04-lacos/node_modules/@vitest/runner/dist/index.js:915:26\n    at file:///home/vicmca/CodeProjects/School/materiais/atv_pub/2c-04-lacos/node_modules/@vitest/runner/dist/index.js:1243:20\n    at new Promise (<anonymous>)\n    at runWithTimeout (file:///home/vicmca/CodeProjects/School/materiais/atv_pub/2c-04-lacos/node_modules/@vitest/runner/dist/index.js:1209:10)\n    at file:///home/vicmca/CodeProjects/School/materiais/atv_pub/2c-04-lacos/node_modules/@vitest/runner/dist/index.js:1653:37\n    at Traces.$ (file:///home/vicmca/CodeProjects/School/materiais/atv_pub/2c-04-lacos/node_modules/vitest/dist/chunks/traces.CCmnQaNT.js:142:27)\n    at trace (file:///home/vicmca/CodeProjects/School/materiais/atv_pub/2c-04-lacos/node_modules/vitest/dist/chunks/test.B8ej_ZHS.js:239:21)\n    at runTest (file:///home/vicmca/CodeProjects/School/materiais/atv_pub/2c-04-lacos/node_modules/@vitest/runner/dist/index.js:1653:12)"],"meta":{}}],"startTime":1776051169002,"endTime":1776051169041.652,"status":"failed","message":"","name":"/home/vicmca/CodeProjects/School/materiais/atv_pub/2c-04-lacos/ex02.test.js"}]}